jinja_components/__init__.py
jinja_components-0.1.0.dist-info/licenses/LICENSE
jinja_components-0.1.0.dist-info/METADATA
jinja_components-0.1.0.dist-info/WHEEL
jinja_components-0.1.0.dist-info/top_level.txt
jinja_components-0.1.0.dist-info/RECORD
