Metadata-Version: 2.4
Name: jinja-components
Version: 0.1.0
Summary: Reusable Jinja2 HTML components and macros for Flask, Django, and Jinja projects.
Home-page: https://github.com/TamerOnLine/jinja-ui
Author: Tamer Hamad Faour
Author-email: info@denkengewinnen.com
Classifier: Programming Language :: Python :: 3
Classifier: License :: OSI Approved :: MIT License
Classifier: Operating System :: OS Independent
Classifier: Framework :: Flask
Classifier: Framework :: Django
Requires-Python: >=3.7
License-File: LICENSE
Requires-Dist: Jinja2>=3.0
Requires-Dist: polib
Requires-Dist: googletrans==4.0.0-rc1
Requires-Dist: Babel
Dynamic: author
Dynamic: author-email
Dynamic: classifier
Dynamic: description
Dynamic: description-content-type
Dynamic: home-page
Dynamic: license-file
Dynamic: requires-dist
Dynamic: requires-python
Dynamic: summary
